{
  "WantedAddress": 128,
  "MinAddress": 128,
  "MaxAddress": 240,
  "AddressClaimWaitPeriodMs": 1250,
  "EcuName": {
    "ArbitraryAddressCapable": true,
    "IndustryGroup": 0,
    "VehicleSystemInstance": 0,
    "VehicalSystem": 127,
    "Function": 255,
    "FunctionInstance": 0,
    "EcuInstance": 0,
    "ManufacturerCode": 2020,
    "IdentityNumber": 55214
  },
  "MqttClient": {
    "BrokerAddress": "172.104.151.160",
    "BrokerPort": 1883,
    "ClientId": "603bcfe769ae7b09a13cfb8c",
    "Username": "scriptTesting",
    "Password": "ErHCPyk#^Up;$P$z",
    "SamplingTimeTopic": "home/garden/fountain",
    "EngineDataPayloadTopic": "home/garden/fountain",
    "ConnectionRetryTimeMilliseconds": 1000
  },
  "EngineModel": "Caterpilar||c32",
  "EngineType": "MAIN",
  "EngineDescription": "Engine 1"
}